{
	"pages": [ //pages数组中第一项表示应用启动页，参考：https://uniapp.dcloud.io/collocation/pages
		{
			"path": "pages/index/index",
			"style": {
				"navigationBarTitleText": "匠心打造-年夜饭"
			}
		},
		{
			"path": "pages/table/table",
			"style": {
				"navigationBarTitleText": "匠心打造-年夜饭"
			}
		},
		{
			"path": "pages/ranking/ranking",
			"style": {
				"navigationBarTitleText": "匠心打造-排行版"
			}
		}
	],
	"globalStyle": {
		"navigationBarTextStyle": "black",
		"navigationBarTitleText": "匠心打造-年夜饭",
		"navigationBarBackgroundColor": "#F8F8F8",
		"backgroundColor": "#F8F8F8"
	}
}
